[
    {
        "fovy": 60.0,
        "name": "EditorCamera",
        "position": [
            -1.4327538013458252,
            6.143893241882324,
            11.076495170593262
        ],
        "projection": 0,
        "target": [
            -1.0416585206985474,
            5.725205421447754,
            10.256895065307617
        ],
        "up": [
            0.0,
            1.0,
            0.0
        ]
    },
    {
        "fovy": 45.0,
        "name": "PlayCamera",
        "position": [
            0.0,
            5.0,
            10.0
        ],
        "projection": 0,
        "target": [
            0.0,
            5.0,
            9.0
        ],
        "up": [
            0.0,
            1.0,
            0.0
        ]
    },
    {
        "color": [
            230,
            41,
            55,
            255
        ],
        "depth": 1.0,
        "height": 1.0,
        "name": "Cube2",
        "type": "Rectangle",
        "uid": 2480095525,
        "width": 1.0,
        "x": 0.0,
        "y": 1.0,
        "z": 0.0
    },
    {
        "color": [
            255,
            255,
            255,
            255
        ],
        "intensity": 1.0,
        "name": "Light0",
        "type": "Light",
        "uid": 1,
        "x": 0.0,
        "y": 2.0,
        "z": 0.0
    }
]